README.md
setup.cfg
setup.py
django_add_default_value/__init__.py
django_add_default_value/add_default_value.py
django_add_default_value_postgresql.egg-info/PKG-INFO
django_add_default_value_postgresql.egg-info/SOURCES.txt
django_add_default_value_postgresql.egg-info/dependency_links.txt
django_add_default_value_postgresql.egg-info/requires.txt
django_add_default_value_postgresql.egg-info/top_level.txt