Metadata-Version: 2.1
Name: django-add-default-value-postgresql
Version: 1.0.0
Summary: Add default field value in Django migrations for PostgreSQL
Home-page: https://github.com/Mariana-Tek/django-add-default-value-postgresql
Author: Mariana Tek
License: Apache-2.0
Keywords: django,migration,default,database backward compatibility
Platform: UNKNOWN
Classifier: Intended Audience :: Developers
Classifier: Environment :: Web Environment
Classifier: Framework :: Django
Classifier: Framework :: Django :: 2.2
Classifier: Framework :: Django :: 3.0
Classifier: License :: OSI Approved :: Apache Software License
Classifier: Programming Language :: Python
Classifier: Programming Language :: Python :: 3
Classifier: Programming Language :: Python :: 3.5
Classifier: Programming Language :: Python :: 3.6
Classifier: Programming Language :: Python :: 3.7
Classifier: Programming Language :: Python :: 3.8
Classifier: Topic :: Software Development :: Libraries :: Python Modules
